icb/__init__.py
icb/icb.py
icb/map.py
icb/definitions/__init__.py
icb/definitions/icb_20210101.py
icb-0.1a3.dist-info/LICENSE
icb-0.1a3.dist-info/METADATA
icb-0.1a3.dist-info/WHEEL
icb-0.1a3.dist-info/top_level.txt
icb-0.1a3.dist-info/RECORD
